src/__init__.py
src/codetrace_pse/__init__.py
src/codetrace_pse/__main__.py
src/codetrace_pse/cli.py
src/codetrace_pse/lib/__init__.py
src/codetrace_pse/lib/scrape.py
codetrace_pse-1.1.0.dist-info/LICENSE
codetrace_pse-1.1.0.dist-info/METADATA
codetrace_pse-1.1.0.dist-info/WHEEL
codetrace_pse-1.1.0.dist-info/entry_points.txt
codetrace_pse-1.1.0.dist-info/top_level.txt
codetrace_pse-1.1.0.dist-info/RECORD
