Metadata-Version: 2.1
Name: codetrace-pse
Version: 1.1.0
Summary: Just another package for GitLab CI/CD Demo
Home-page: https://gitlab.com/melcdn/codetrace-pse
Author: Mel Cadano
Author-email: mel.cdn@outlook.ph
License: UNKNOWN
Platform: UNKNOWN
Requires-Dist: requests
Requires-Dist: beautifulsoup4
